limberframework/__init__.py
limberframework/authentication/__init__.py
limberframework/authentication/authentication_service_provider.py
limberframework/authentication/authenticators.py
limberframework/cache/__init__.py
limberframework/cache/cache.py
limberframework/cache/cache_service_provider.py
limberframework/cache/exceptions.py
limberframework/cache/lockers.py
limberframework/cache/stores.py
limberframework/config/__init__.py
limberframework/config/config.py
limberframework/config/config_service_provider.py
limberframework/database/__init__.py
limberframework/database/connections.py
limberframework/database/database_service_provider.py
limberframework/database/middleware.py
limberframework/database/models.py
limberframework/filesystem/__init__.py
limberframework/filesystem/filesystem.py
limberframework/foundation/__init__.py
limberframework/foundation/application.py
limberframework/hashing/__init__.py
limberframework/hashing/hashers.py
limberframework/routing/__init__.py
limberframework/routing/exceptions.py
limberframework/routing/middleware.py
limberframework/routing/rate_limiter.py
limberframework/support/__init__.py
limberframework/support/services.py
limberframework-0.2.0.dist-info/LICENSE.txt
limberframework-0.2.0.dist-info/WHEEL
limberframework-0.2.0.dist-info/METADATA
limberframework-0.2.0.dist-info/RECORD
