Metadata-Version: 2.1
Name: limberframework
Version: 0.2.0
Summary: The core of the Limber Framework, a python web application framework built using FastAPI.
Home-page: https://github.com/limber-project/limberframework
License: MIT
Keywords: python,fastapi
Author: Jonathan Staniforth
Author-email: jonathanstaniforth@gmail.com
Requires-Python: >=3.8,<=3.9.0
Classifier: License :: OSI Approved :: MIT License
Classifier: Programming Language :: Python :: 3
Classifier: Programming Language :: Python :: 3.8
Requires-Dist: aioredis (>=1.3.1,<2.0.0)
Requires-Dist: aioredlock (>=0.5.2,<0.6.0)
Requires-Dist: fastapi (==0.59.0)
Requires-Dist: psycopg2 (==2.8.5)
Requires-Dist: pydantic (==1.6.1)
Requires-Dist: pymemcache (==3.2.0)
Requires-Dist: redis (==3.5.3)
Requires-Dist: sqlalchemy (==1.3.18)
Project-URL: Documentation, https://github.com/limber-project/limberframework/wiki
Project-URL: Repository, https://github.com/limber-project/limberframework
